ocxsect.py
ocxsect-0.1.5.dist-info/LICENSE
ocxsect-0.1.5.dist-info/METADATA
ocxsect-0.1.5.dist-info/WHEEL
ocxsect-0.1.5.dist-info/top_level.txt
ocxsect-0.1.5.dist-info/RECORD
