Metadata-Version: 2.1
Name: ocxsect
Version: 0.1.5
Summary: A python markdown extension that allows you to add semantic HTML5 sectioning elements into the generated html.
Home-page: https://github.com/philbarker/ocxsect
Author: Phil Barker
Author-email: phil.barker@pjjk.co.uk
License: Apache2
Platform: UNKNOWN
Classifier: Development Status :: 4 - Beta
Classifier: License :: OSI Approved :: Apache Software License
Classifier: Topic :: Text Processing :: Markup :: HTML
Classifier: Programming Language :: Python :: 3.6
Classifier: Programming Language :: Python :: 3.7
Requires-Dist: setuptools (>=40.6)
